LICENSE
README.md
setup.py
pyTaskify.egg-info/PKG-INFO
pyTaskify.egg-info/SOURCES.txt
pyTaskify.egg-info/dependency_links.txt
pyTaskify.egg-info/entry_points.txt
pyTaskify.egg-info/requires.txt
pyTaskify.egg-info/top_level.txt
pytaskify/__init__.py
pytaskify/cli.py
pytaskify/config.py
pytaskify/executor.py
pytaskify/helpers.py
pytaskify/tasks.py
pytaskify/version.py