Metadata-Version: 2.1
Name: pyTaskify
Version: 0.0.2
Summary: A Task Runner written in Python
Home-page: https://github.com/AlisonVilela/pyTaskify
Author: Alison Vilela
Author-email: vilela@alison.dev
License: UNKNOWN
Platform: UNKNOWN
Classifier: Development Status :: 3 - Alpha
Classifier: Intended Audience :: Developers
Classifier: License :: OSI Approved :: MIT License
Classifier: Programming Language :: Python
Classifier: Programming Language :: Python :: 3
Classifier: Programming Language :: Python :: 3.7
Classifier: Programming Language :: Python :: 3.8
Classifier: Programming Language :: Python :: 3.9
Classifier: Operating System :: OS Independent
License-File: LICENSE
